libname/__init__.py
libname/helpful_functions.py
miki_helpful_functions-0.0.1.dist-info/METADATA
miki_helpful_functions-0.0.1.dist-info/WHEEL
miki_helpful_functions-0.0.1.dist-info/top_level.txt
miki_helpful_functions-0.0.1.dist-info/RECORD
