Metadata-Version: 2.1
Name: miki-helpful-functions
Version: 0.0.1
Summary: This is a package with some helpful functions =D
Home-page: UNKNOWN
Author: NeuralNine (Florian Dedov)
Author-email: <vinicius_miki@hotmail.com>
License: UNKNOWN
Platform: UNKNOWN
Classifier: Development Status :: 1 - Planning
Classifier: Intended Audience :: Developers
Classifier: Programming Language :: Python :: 3
Classifier: Operating System :: Unix
Classifier: Operating System :: MacOS :: MacOS X
Classifier: Operating System :: Microsoft :: Windows
